asdk_plugin_trading/__init__.py
asdk_plugin_trading/api_registry.py
asdk_plugin_trading/domain_apis_list.json
asdk_plugin_trading/agraph/__init__.py
asdk_plugin_trading/agraph/trading/__init__.py
asdk_plugin_trading/agraph/trading/order_management/__init__.py
asdk_plugin_trading/agraph/trading/order_management/order/__init__.py
asdk_plugin_trading/agraph/trading/order_management/order/v1/__init__.py
asdk_plugin_trading/agraph/trading/order_management/order/v1/OrderAPI/__init__.py
asdk_plugin_trading/agraph/trading/order_management/order/v1/OrderAPI/api_client.py
asdk_plugin_trading/agraph/trading/order_management/order/v1/OrderAPI/api_response.py
asdk_plugin_trading/agraph/trading/order_management/order/v1/OrderAPI/configuration.py
asdk_plugin_trading/agraph/trading/order_management/order/v1/OrderAPI/exceptions.py
asdk_plugin_trading/agraph/trading/order_management/order/v1/OrderAPI/rest.py
asdk_plugin_trading/agraph/trading/order_management/order/v1/OrderAPI/swagger.json
asdk_plugin_trading/agraph/trading/order_management/order/v1/OrderAPI/api/__init__.py
asdk_plugin_trading/agraph/trading/order_management/order/v1/OrderAPI/api/default_order_api.py
asdk_plugin_trading/agraph/trading/order_management/order/v1/OrderAPI/models/__init__.py
asdk_plugin_trading/agraph/trading/order_management/order/v1/OrderAPI/models/any.py
asdk_plugin_trading/agraph/trading/order_management/order/v1/OrderAPI/models/enums_assigned_to_status.py
asdk_plugin_trading/agraph/trading/order_management/order/v1/OrderAPI/models/enums_compliance_position_source.py
asdk_plugin_trading/agraph/trading/order_management/order/v1/OrderAPI/models/enums_compliance_severity.py
asdk_plugin_trading/agraph/trading/order_management/order/v1/OrderAPI/models/enums_financing_type.py
asdk_plugin_trading/agraph/trading/order_management/order/v1/OrderAPI/models/enums_order_reservation_status.py
asdk_plugin_trading/agraph/trading/order_management/order/v1/OrderAPI/models/enums_order_reservation_type.py
asdk_plugin_trading-2.0.0b2.dist-info/METADATA
asdk_plugin_trading-2.0.0b2.dist-info/WHEEL
asdk_plugin_trading-2.0.0b2.dist-info/top_level.txt
asdk_plugin_trading-2.0.0b2.dist-info/RECORD
